uncurl/__init__.py
uncurl/api.py
uncurl/bin.py
uncurl-0.0.11.dist-info/LICENSE
uncurl-0.0.11.dist-info/METADATA
uncurl-0.0.11.dist-info/WHEEL
uncurl-0.0.11.dist-info/entry_points.txt
uncurl-0.0.11.dist-info/top_level.txt
uncurl-0.0.11.dist-info/RECORD
