Metadata-Version: 1.0
Name: uncurl
Version: 0.0.11
Summary: A library to convert curl requests to python-requests.
Home-page: https://github.com/spulec/uncurl
Author: Steve Pulec
Author-email: spulec@gmail.com
License: UNKNOWN
Platform: UNKNOWN
